{
  "v": "5.7.4",
  "fr": 30,
  "ip": 0,
  "op": 60,
  "w": 512,
  "h": 512,
  "nm": "Plant Sprout Refined",
  "ddd": 0,
  "assets": [],
  "layers": [
    {
      "ddd": 0,
      "ind": 1,
      "ty": 4,
      "nm": "Sprout Scene",
      "sr": 1,
      "ks": {
        "o": { "a": 0, "k": 100 },
        "r": { "a": 0, "k": 0 },
        "p": { "a": 0, "k": [0, 0, 0] },
        "a": { "a": 0, "k": [0, 0, 0] },
        "s": { "a": 0, "k": [100, 100, 100] }
      },
      "ao": 0,
      "shapes": [
        {
          "ty": "gr",
          "it": [
            { "ty": "el", "p": { "a": 0, "k": [256, 212] }, "s": { "a": 0, "k": [300, 300] }, "d": 1, "nm": "Halo Outer" },
            { "ty": "fl", "c": { "a": 0, "k": [0.88, 0.94, 0.89, 1] }, "o": { "a": 0, "k": 24 }, "r": 1, "nm": "Halo Outer Fill" },
            { "ty": "tr", "p": { "a": 0, "k": [0, 0] }, "a": { "a": 0, "k": [0, 0] }, "s": { "a": 0, "k": [100, 100] }, "r": { "a": 0, "k": 0 }, "o": { "a": 0, "k": 100 }, "sk": { "a": 0, "k": 0 }, "sa": { "a": 0, "k": 0 } }
          ],
          "nm": "Halo Outer Group"
        },
        {
          "ty": "gr",
          "it": [
            { "ty": "el", "p": { "a": 0, "k": [256, 402] }, "s": { "a": 0, "k": [194, 30] }, "d": 1, "nm": "Shadow" },
            { "ty": "fl", "c": { "a": 0, "k": [0.41, 0.34, 0.31, 1] }, "o": { "a": 0, "k": 14 }, "r": 1, "nm": "Shadow Fill" },
            { "ty": "tr", "p": { "a": 0, "k": [0, 0] }, "a": { "a": 0, "k": [0, 0] }, "s": { "a": 0, "k": [100, 100] }, "r": { "a": 0, "k": 0 }, "o": { "a": 0, "k": 100 }, "sk": { "a": 0, "k": 0 }, "sa": { "a": 0, "k": 0 } }
          ],
          "nm": "Shadow Group"
        },
        {
          "ty": "gr",
          "it": [
            { "ty": "rc", "p": { "a": 0, "k": [256, 372] }, "s": { "a": 0, "k": [186, 126] }, "r": { "a": 0, "k": 38 }, "nm": "Pot Body" },
            { "ty": "fl", "c": { "a": 0, "k": [0.89, 0.75, 0.69, 1] }, "o": { "a": 0, "k": 100 }, "r": 1, "nm": "Pot Body Fill" },
            { "ty": "tr", "p": { "a": 0, "k": [0, 0] }, "a": { "a": 0, "k": [0, 0] }, "s": { "a": 0, "k": [100, 100] }, "r": { "a": 0, "k": 0 }, "o": { "a": 0, "k": 100 }, "sk": { "a": 0, "k": 0 }, "sa": { "a": 0, "k": 0 } }
          ],
          "nm": "Pot Body Group"
        },
        {
          "ty": "gr",
          "it": [
            { "ty": "rc", "p": { "a": 0, "k": [256, 278] }, "s": { "a": 0, "k": [16, 124] }, "r": { "a": 0, "k": 12 }, "nm": "Stem" },
            { "ty": "fl", "c": { "a": 0, "k": [0.49, 0.72, 0.55, 1] }, "o": { "a": 0, "k": 100 }, "r": 1, "nm": "Stem Fill" },
            { "ty": "tr", "p": { "a": 0, "k": [0, 0] }, "a": { "a": 0, "k": [0, 0] }, "s": { "a": 0, "k": [100, 100] }, "r": { "a": 0, "k": 0 }, "o": { "a": 0, "k": 100 }, "sk": { "a": 0, "k": 0 }, "sa": { "a": 0, "k": 0 } }
          ],
          "nm": "Stem Group"
        },
        {
          "ty": "gr",
          "it": [
            { "ty": "el", "p": { "a": 0, "k": [218, 222] }, "s": { "a": 0, "k": [110, 58] }, "d": 1, "nm": "Leaf Left" },
            { "ty": "fl", "c": { "a": 0, "k": [0.73, 0.88, 0.72, 1] }, "o": { "a": 0, "k": 100 }, "r": 1, "nm": "Leaf Left Fill" },
            { "ty": "tr", "p": { "a": 0, "k": [0, 0] }, "a": { "a": 0, "k": [218, 222] }, "s": { "a": 0, "k": [100, 100] }, "r": { "a": 0, "k": -28 }, "o": { "a": 0, "k": 100 }, "sk": { "a": 0, "k": 0 }, "sa": { "a": 0, "k": 0 } }
          ],
          "nm": "Leaf Left Group"
        },
        {
          "ty": "gr",
          "it": [
            { "ty": "el", "p": { "a": 0, "k": [294, 220] }, "s": { "a": 0, "k": [110, 58] }, "d": 1, "nm": "Leaf Right" },
            { "ty": "fl", "c": { "a": 0, "k": [0.73, 0.88, 0.72, 1] }, "o": { "a": 0, "k": 100 }, "r": 1, "nm": "Leaf Right Fill" },
            { "ty": "tr", "p": { "a": 0, "k": [0, 0] }, "a": { "a": 0, "k": [294, 220] }, "s": { "a": 0, "k": [100, 100] }, "r": { "a": 0, "k": 28 }, "o": { "a": 0, "k": 100 }, "sk": { "a": 0, "k": 0 }, "sa": { "a": 0, "k": 0 } }
          ],
          "nm": "Leaf Right Group"
        },
        {
          "ty": "gr",
          "it": [
            { "ty": "el", "p": { "a": 0, "k": [256, 192] }, "s": { "a": 0, "k": [22, 22] }, "d": 1, "nm": "Bud" },
            { "ty": "fl", "c": { "a": 0, "k": [0.90, 0.82, 0.59, 1] }, "o": { "a": 0, "k": 100 }, "r": 1, "nm": "Bud Fill" },
            { "ty": "tr", "p": { "a": 0, "k": [0, 0] }, "a": { "a": 0, "k": [0, 0] }, "s": { "a": 0, "k": [100, 100] }, "r": { "a": 0, "k": 0 }, "o": { "a": 0, "k": 100 }, "sk": { "a": 0, "k": 0 }, "sa": { "a": 0, "k": 0 } }
          ],
          "nm": "Bud Group"
        },
        {
          "ty": "gr",
          "it": [
            { "ty": "el", "p": { "a": 0, "k": [256, 332] }, "s": { "a": 0, "k": [146, 24] }, "d": 1, "nm": "Soil" },
            { "ty": "fl", "c": { "a": 0, "k": [0.53, 0.40, 0.31, 1] }, "o": { "a": 0, "k": 100 }, "r": 1, "nm": "Soil Fill" },
            { "ty": "tr", "p": { "a": 0, "k": [0, 0] }, "a": { "a": 0, "k": [0, 0] }, "s": { "a": 0, "k": [100, 100] }, "r": { "a": 0, "k": 0 }, "o": { "a": 0, "k": 100 }, "sk": { "a": 0, "k": 0 }, "sa": { "a": 0, "k": 0 } }
          ],
          "nm": "Soil Group"
        },
        {
          "ty": "gr",
          "it": [
            { "ty": "rc", "p": { "a": 0, "k": [256, 324] }, "s": { "a": 0, "k": [210, 38] }, "r": { "a": 0, "k": 22 }, "nm": "Pot Rim" },
            { "ty": "fl", "c": { "a": 0, "k": [0.95, 0.84, 0.79, 1] }, "o": { "a": 0, "k": 100 }, "r": 1, "nm": "Pot Rim Fill" },
            { "ty": "tr", "p": { "a": 0, "k": [0, 0] }, "a": { "a": 0, "k": [0, 0] }, "s": { "a": 0, "k": [100, 100] }, "r": { "a": 0, "k": 0 }, "o": { "a": 0, "k": 100 }, "sk": { "a": 0, "k": 0 }, "sa": { "a": 0, "k": 0 } }
          ],
          "nm": "Pot Rim Group"
        },
        {
          "ty": "gr",
          "it": [
            { "ty": "rc", "p": { "a": 0, "k": [206, 372] }, "s": { "a": 0, "k": [28, 86] }, "r": { "a": 0, "k": 16 }, "nm": "Pot Highlight" },
            { "ty": "fl", "c": { "a": 0, "k": [1, 1, 1, 1] }, "o": { "a": 0, "k": 18 }, "r": 1, "nm": "Pot Highlight Fill" },
            { "ty": "tr", "p": { "a": 0, "k": [0, 0] }, "a": { "a": 0, "k": [0, 0] }, "s": { "a": 0, "k": [100, 100] }, "r": { "a": 0, "k": 0 }, "o": { "a": 0, "k": 100 }, "sk": { "a": 0, "k": 0 }, "sa": { "a": 0, "k": 0 } }
          ],
          "nm": "Pot Highlight Group"
        }
      ],
      "ip": 0,
      "op": 60,
      "st": 0,
      "bm": 0
    }
  ]
}
